geomac_wildfires/__init__.py
geomac_wildfires/cli.py
geomac_wildfires-0.1.14.dist-info/LICENSE
geomac_wildfires-0.1.14.dist-info/METADATA
geomac_wildfires-0.1.14.dist-info/WHEEL
geomac_wildfires-0.1.14.dist-info/entry_points.txt
geomac_wildfires-0.1.14.dist-info/top_level.txt
geomac_wildfires-0.1.14.dist-info/RECORD
