Metadata-Version: 2.1
Name: geomac-wildfires
Version: 0.1.14
Summary: Download wildfires data from NIFC
Home-page: http://www.github.com/datadesk/geomac-wildfires
Author: Los Angeles Times Data and Graphics Department
Author-email: datagraphics@latimes.com
License: MIT
Project-URL: Maintainer, https://github.com/datadesk
Project-URL: Source, https://github.com/datadesk/geomac-wildfires
Project-URL: Tracker, https://github.com/datadesk/geomac-wildfires/issues
Project-URL: CI, https://travis-ci.org/datadesk/geomac-wildfires/
Platform: UNKNOWN
Classifier: Development Status :: 5 - Production/Stable
Classifier: Programming Language :: Python
Classifier: Programming Language :: Python :: 3.6
Classifier: Programming Language :: Python :: 3.7
Classifier: License :: OSI Approved :: MIT License
Requires-Dist: requests
Requires-Dist: fiona
Requires-Dist: geojson
Requires-Dist: click
